annoying/__init__.py
annoying/decorators.py
annoying/exceptions.py
annoying/fields.py
annoying/functions.py
annoying/middlewares.py
annoying/py.typed
annoying/utils.py
django_annoying-0.10.8.dist-info/LICENSE.txt
django_annoying-0.10.8.dist-info/METADATA
django_annoying-0.10.8.dist-info/WHEEL
django_annoying-0.10.8.dist-info/top_level.txt
django_annoying-0.10.8.dist-info/RECORD
